qcanvas_api_clients/__init__.py
qcanvas_api_clients/canvas/__init__.py
qcanvas_api_clients/canvas/canvas_authenticator.py
qcanvas_api_clients/canvas/canvas_client.py
qcanvas_api_clients/canvas/canvas_client_config.py
qcanvas_api_clients/canvas/canvas_types.py
qcanvas_api_clients/canvas/canvas_unauthenticated_detector_hook.py
qcanvas_api_clients/panopto/__init__.py
qcanvas_api_clients/panopto/fake_panopto_client.py
qcanvas_api_clients/panopto/panopto_authenticator.py
qcanvas_api_clients/panopto/panopto_client.py
qcanvas_api_clients/panopto/panopto_client_config.py
qcanvas_api_clients/panopto/panopto_types.py
qcanvas_api_clients/panopto/panopto_unauthenticated_detector_hook.py
qcanvas_api_clients/util/__init__.py
qcanvas_api_clients/util/add_cookies_to_request_hook.py
qcanvas_api_clients/util/authenticator.py
qcanvas_api_clients/util/cachedasyncmethod_for_development.py
qcanvas_api_clients/util/external_client_httpx_transport.py
qcanvas_api_clients/util/json_util.py
qcanvas_api_clients/util/request_exceptions.py
qcanvas_api_clients/util/url_converter.py
qcanvas_api_clients-0.5.1.dist-info/METADATA
qcanvas_api_clients-0.5.1.dist-info/WHEEL
qcanvas_api_clients-0.5.1.dist-info/RECORD
